htrfnwe.cpython-37m-x86_64-linux-gnu.so
htrfnwe-0.8.dist-info/WHEEL
htrfnwe-0.8.dist-info/top_level.txt
htrfnwe-0.8.dist-info/METADATA
htrfnwe-0.8.dist-info/RECORD
htrfnwe/TestLinuxCythonichtrfnwe.py
