Metadata-Version: 2.1
Name: htrfnwe
Version: 0.8
Summary: A package with multiple Cython programs for technical analysis
Home-page: https://github.com/Liteshi55/htrfnwe
Author: Litesh
Author-email: liteshi55@gmail.com
Classifier: Programming Language :: Python
Classifier: Programming Language :: Cython
Classifier: License :: OSI Approved :: MIT License
Classifier: Operating System :: OS Independent
Requires-Python: >=3.6
Requires-Dist: numpy
Requires-Dist: scikit-learn
Requires-Dist: Cython
Requires-Dist: pandas
